pyhiit/__init__.py
py_hiit-0.0.1.dist-info/METADATA
py_hiit-0.0.1.dist-info/WHEEL
py_hiit-0.0.1.dist-info/top_level.txt
py_hiit-0.0.1.dist-info/RECORD
